<record xmlns="http://www.openarchives.org/OAI/2.0/" xmlns:xsi="http://www.w3.org/2001/XMLSchema-instance"><header><identifier>oai:oai.datacite.org:1222209</identifier><datestamp>2014-05-30T00:06:58Z</datestamp><setSpec>CDL</setSpec><setSpec>CDL.DRYAD</setSpec></header><metadata><oai_datacite xmlns="http://schema.datacite.org/oai/oai-1.0/" xsi:schemaLocation="http://schema.datacite.org/oai/oai-1.0/ http://schema.datacite.org/oai/oai-1.0/oai.xsd"><isReferenceQuality>false</isReferenceQuality><schemaVersion>2.2</schemaVersion><datacentreSymbol>CDL.DRYAD</datacentreSymbol><payload><resource xmlns="http://datacite.org/schema/kernel-2.2" xmlns:dryad="http://purl.org/dryad/terms/" xmlns:dim="http://www.dspace.org/xmlns/dspace/dim" xmlns:dspace="http://www.dspace.org/xmlns/dspace/dim" xmlns:mets="http://www.loc.gov/METS/" xmlns:xsi="http://www.w3.org/2001/XMLSchema-instance" metadataVersionNumber="1" lastMetadataUpdate="2006-05-04" xsi:schemaLocation="http://datacite.org/schema/kernel-2.2 http://schema.datacite.org/meta/kernel-2.2/metadata.xsd">
  <identifier identifierType="DOI">10.5061/DRYAD.0MQ69</identifier>
  <creators>
      <creator>
         <creatorName>Harnik, Paul G.</creatorName>
      </creator>
      <creator>
         <creatorName>Simpson, Carl</creatorName>
      </creator>
      <creator>
         <creatorName>Payne, Jonathan L.</creatorName>
      </creator>
  </creators>
  <titles>
      <title>Data from: Long-term differences in extinction risk among the seven forms of rarity</title>
  </titles>
  <publisher>Dryad Digital Repository</publisher>
  <publicationYear>2012</publicationYear>
  <subjects>
      <subject>macroevolution</subject>
      <subject>macroecology</subject>
      <subject>paleobiology</subject>
      <subject>fossils</subject>
      <subject>conservation</subject>
      <subject>Marine invertebrates</subject>
      <subject>Global</subject>
      <subject>Phanerozoic</subject>
      <subject>Paleozoic</subject>
      <subject>Mesozoic</subject>
      <subject>Cenozoic</subject>
      <subject>Bivalvia</subject>
      <subject>Gastropoda</subject>
      <subject>Brachiopoda</subject>
      <subject>Protozoa</subject>
      <subject>Porifera</subject>
      <subject>Mollusca</subject>
      <subject>Arthropoda</subject>
      <subject>Echinodermata</subject>
      <subject>Bryozoa</subject>
      <subject>Cnidaria</subject>
  </subjects>
  <resourceType resourceTypeGeneral="Dataset">DataPackage</resourceType>
  <alternateIdentifiers>
      <alternateIdentifier alternateIdentifierType="citation">Harnik PG, Simpson C, Payne JL (2012) Long-term differences in extinction risk among the seven forms of rarity. Proceedings of the Royal Society B 279(1749): 4969-4976.</alternateIdentifier>
  </alternateIdentifiers>
  <relatedIdentifiers>
      <relatedIdentifier relationType="HasPart" relatedIdentifierType="DOI">10.5061/DRYAD.0MQ69/1</relatedIdentifier>
      <relatedIdentifier relationType="HasPart" relatedIdentifierType="DOI">10.5061/DRYAD.0MQ69/2</relatedIdentifier>
      <relatedIdentifier relationType="IsReferencedBy" relatedIdentifierType="DOI">10.1098/RSPB.2012.1902</relatedIdentifier>
      <relatedIdentifier relationType="IsReferencedBy" relatedIdentifierType="DOI"/>
  </relatedIdentifiers>
  <rights>http://creativecommons.org/publicdomain/zero/1.0/</rights>
</resource></payload></oai_datacite></metadata></record>
