<record xmlns="http://www.openarchives.org/OAI/2.0/" xmlns:xsi="http://www.w3.org/2001/XMLSchema-instance"><header><identifier>oai:oai.datacite.org:1727281</identifier><datestamp>2014-05-30T02:28:51Z</datestamp><setSpec>CDL</setSpec><setSpec>CDL.DRYAD</setSpec></header><metadata><oai_datacite xmlns="http://schema.datacite.org/oai/oai-1.0/" xsi:schemaLocation="http://schema.datacite.org/oai/oai-1.0/ http://schema.datacite.org/oai/oai-1.0/oai.xsd"><isReferenceQuality>false</isReferenceQuality><schemaVersion>2.2</schemaVersion><datacentreSymbol>CDL.DRYAD</datacentreSymbol><payload><resource xmlns="http://datacite.org/schema/kernel-2.2" xmlns:dryad="http://purl.org/dryad/terms/" xmlns:dim="http://www.dspace.org/xmlns/dspace/dim" xmlns:dspace="http://www.dspace.org/xmlns/dspace/dim" xmlns:mets="http://www.loc.gov/METS/" xmlns:xsi="http://www.w3.org/2001/XMLSchema-instance" metadataVersionNumber="1" lastMetadataUpdate="2006-05-04" xsi:schemaLocation="http://datacite.org/schema/kernel-2.2 http://schema.datacite.org/meta/kernel-2.2/metadata.xsd">
  <identifier identifierType="DOI">10.5061/DRYAD.18790</identifier>
  <creators>
      <creator>
         <creatorName>Temperli, Christian</creatorName>
      </creator>
      <creator>
         <creatorName>Bugmann, Harald K. M.</creatorName>
      </creator>
      <creator>
         <creatorName>Elkin, Ch&#233;</creatorName>
      </creator>
  </creators>
  <titles>
      <title>Data from: Cross-scale interactions among bark beetles, climate change and wind disturbances a landscape modeling approach</title>
  </titles>
  <publisher>Dryad Digital Repository</publisher>
  <publicationYear>2013</publicationYear>
  <subjects>
      <subject>bark beetles</subject>
      <subject>climate change</subject>
      <subject>disturbance interactions</subject>
      <subject>forest dynamics</subject>
      <subject>LandClim</subject>
      <subject>landscape model</subject>
      <subject>management strategy</subject>
      <subject>regime shift</subject>
      <subject>European spruce bark beetle</subject>
      <subject>Norway spruce</subject>
      <subject>Central Europe</subject>
      <subject>Ips typographus</subject>
      <subject>Picea abies</subject>
  </subjects>
  <resourceType resourceTypeGeneral="Dataset">DataPackage</resourceType>
  <alternateIdentifiers>
      <alternateIdentifier alternateIdentifierType="citation">Temperli C, Bugmann HKM, Elkin C (2013) Cross-scale interactions among bark beetles, climate change and wind disturbances a landscape modeling approach. Ecological Monographs 83(3): 383-402.</alternateIdentifier>
  </alternateIdentifiers>
  <relatedIdentifiers>
      <relatedIdentifier relationType="HasPart" relatedIdentifierType="DOI">10.5061/DRYAD.18790/1</relatedIdentifier>
      <relatedIdentifier relationType="HasPart" relatedIdentifierType="DOI">10.5061/DRYAD.18790/2</relatedIdentifier>
      <relatedIdentifier relationType="IsReferencedBy" relatedIdentifierType="DOI">10.1890/12-1503.1</relatedIdentifier>
  </relatedIdentifiers>
  <rights>http://creativecommons.org/publicdomain/zero/1.0/</rights>
</resource></payload></oai_datacite></metadata></record>
