<record xmlns="http://www.openarchives.org/OAI/2.0/" xmlns:xsi="http://www.w3.org/2001/XMLSchema-instance"><header><identifier>oai:oai.datacite.org:2825557</identifier><datestamp>2014-05-30T09:16:24Z</datestamp><setSpec>CDL</setSpec><setSpec>CDL.DRYAD</setSpec></header><metadata><oai_datacite xmlns="http://schema.datacite.org/oai/oai-1.0/" xsi:schemaLocation="http://schema.datacite.org/oai/oai-1.0/ http://schema.datacite.org/oai/oai-1.0/oai.xsd"><isReferenceQuality>false</isReferenceQuality><schemaVersion>2.2</schemaVersion><datacentreSymbol>CDL.DRYAD</datacentreSymbol><payload><resource xmlns="http://datacite.org/schema/kernel-2.2" xmlns:dryad="http://purl.org/dryad/terms/" xmlns:dim="http://www.dspace.org/xmlns/dspace/dim" xmlns:dspace="http://www.dspace.org/xmlns/dspace/dim" xmlns:mets="http://www.loc.gov/METS/" xmlns:xsi="http://www.w3.org/2001/XMLSchema-instance" metadataVersionNumber="1" lastMetadataUpdate="2006-05-04" xsi:schemaLocation="http://datacite.org/schema/kernel-2.2 http://schema.datacite.org/meta/kernel-2.2/metadata.xsd">
  <identifier identifierType="DOI">10.5061/DRYAD.B5J25</identifier>
  <creators>
      <creator>
         <creatorName>Charg&#233;, R&#233;mi</creatorName>
      </creator>
      <creator>
         <creatorName>Sorci, Gabriele</creatorName>
      </creator>
      <creator>
         <creatorName>Saint Jalme, Michel</creatorName>
      </creator>
      <creator>
         <creatorName>Lesobre, Lo&#239;c</creatorName>
      </creator>
      <creator>
         <creatorName>Hingrat, Yves</creatorName>
      </creator>
      <creator>
         <creatorName>Lacroix, Fr&#233;d&#233;ric</creatorName>
      </creator>
      <creator>
         <creatorName>Teplitsky, Celine</creatorName>
      </creator>
  </creators>
  <titles>
      <title>Data from: Does recognized genetic management in supportive breeding prevent genetic changes in life-history traits?</title>
  </titles>
  <publisher>Dryad Digital Repository</publisher>
  <publicationYear>2014</publicationYear>
  <subjects>
      <subject>Conservation Genetics</subject>
      <subject>Quantitative Genetics</subject>
      <subject>Captive Populations</subject>
      <subject>North Africa</subject>
      <subject>21th century</subject>
      <subject>chlamydotis undulata</subject>
  </subjects>
  <resourceType resourceTypeGeneral="Dataset">DataPackage</resourceType>
  <alternateIdentifiers>
      <alternateIdentifier alternateIdentifierType="citation">Charg&#233; R, Sorci G, Saint Jalme M, Lesobre L, Hingrat Y, Lacroix F, Teplitsky C (2014) Does recognized genetic management in supportive breeding prevent genetic changes in life-history traits? Evolutionary Applications 7(5): 521&#8211;532.</alternateIdentifier>
  </alternateIdentifiers>
  <relatedIdentifiers>
      <relatedIdentifier relationType="HasPart" relatedIdentifierType="DOI">10.5061/DRYAD.B5J25/1</relatedIdentifier>
      <relatedIdentifier relationType="IsReferencedBy" relatedIdentifierType="DOI">10.1111/EVA.12150</relatedIdentifier>
  </relatedIdentifiers>
  <rights>http://creativecommons.org/publicdomain/zero/1.0/</rights>
</resource></payload></oai_datacite></metadata></record>
