<record xmlns="http://www.openarchives.org/OAI/2.0/" xmlns:xsi="http://www.w3.org/2001/XMLSchema-instance"><header><identifier>oai:oai.datacite.org:3504699</identifier><datestamp>2014-05-30T09:22:48Z</datestamp><setSpec>CDL</setSpec><setSpec>CDL.DRYAD</setSpec></header><metadata><oai_datacite xmlns="http://schema.datacite.org/oai/oai-1.0/" xsi:schemaLocation="http://schema.datacite.org/oai/oai-1.0/ http://schema.datacite.org/oai/oai-1.0/oai.xsd"><isReferenceQuality>false</isReferenceQuality><schemaVersion>2.2</schemaVersion><datacentreSymbol>CDL.DRYAD</datacentreSymbol><payload><resource xmlns="http://datacite.org/schema/kernel-2.2" xmlns:dryad="http://purl.org/dryad/terms/" xmlns:dim="http://www.dspace.org/xmlns/dspace/dim" xmlns:dspace="http://www.dspace.org/xmlns/dspace/dim" xmlns:mets="http://www.loc.gov/METS/" xmlns:xsi="http://www.w3.org/2001/XMLSchema-instance" metadataVersionNumber="1" lastMetadataUpdate="2006-05-04" xsi:schemaLocation="http://datacite.org/schema/kernel-2.2 http://schema.datacite.org/meta/kernel-2.2/metadata.xsd">
  <identifier identifierType="DOI">10.5061/DRYAD.7H6P6</identifier>
  <creators>
      <creator>
         <creatorName>Tolonen, Kimmo T.</creatorName>
      </creator>
      <creator>
         <creatorName>H&#228;m&#228;l&#228;inen, Heikki</creatorName>
      </creator>
      <creator>
         <creatorName>Lensu, Anssi</creatorName>
      </creator>
      <creator>
         <creatorName>Meril&#228;inen, Jarmo J.</creatorName>
      </creator>
      <creator>
         <creatorName>Palom&#228;ki, Arja</creatorName>
      </creator>
      <creator>
         <creatorName>Karjalainen, Juha</creatorName>
      </creator>
  </creators>
  <titles>
      <title>Data from: The relevance of ecological status to ecosystem functions and services in a large boreal lake</title>
  </titles>
  <publisher>Dryad Digital Repository</publisher>
  <publicationYear>2014</publicationYear>
  <subjects>
      <subject>bioassessment</subject>
      <subject>biodiversity</subject>
      <subject>ecological classification</subject>
      <subject>lake ecosystems</subject>
      <subject>lake management</subject>
      <subject>lake recovery</subject>
      <subject>Water Framework Directive</subject>
      <subject>ecosystem services</subject>
      <subject>ecosystem functions</subject>
      <subject>Northern Europe</subject>
      <subject>Holocene</subject>
  </subjects>
  <resourceType resourceTypeGeneral="Dataset">DataPackage</resourceType>
  <alternateIdentifiers>
      <alternateIdentifier alternateIdentifierType="citation">Tolonen KT, H&#228;m&#228;l&#228;inen H, Lensu A, Meril&#228;inen JJ, Palom&#228;ki A, Karjalainen J (2014) The relevance of ecological status to ecosystem functions and services in a large boreal lake. Journal of Applied Ecology 51(3): 560&#8211;571.</alternateIdentifier>
  </alternateIdentifiers>
  <relatedIdentifiers>
      <relatedIdentifier relationType="HasPart" relatedIdentifierType="DOI">10.5061/DRYAD.7H6P6/1</relatedIdentifier>
      <relatedIdentifier relationType="HasPart" relatedIdentifierType="DOI">10.5061/DRYAD.7H6P6/2</relatedIdentifier>
      <relatedIdentifier relationType="HasPart" relatedIdentifierType="DOI">10.5061/DRYAD.7H6P6/3</relatedIdentifier>
      <relatedIdentifier relationType="HasPart" relatedIdentifierType="DOI">10.5061/DRYAD.7H6P6/4</relatedIdentifier>
      <relatedIdentifier relationType="HasPart" relatedIdentifierType="DOI">10.5061/DRYAD.7H6P6/5</relatedIdentifier>
      <relatedIdentifier relationType="IsReferencedBy" relatedIdentifierType="DOI">10.1111/1365-2664.12245</relatedIdentifier>
  </relatedIdentifiers>
  <rights>http://creativecommons.org/publicdomain/zero/1.0/</rights>
</resource></payload></oai_datacite></metadata></record>
