<record xmlns="http://www.openarchives.org/OAI/2.0/" xmlns:xsi="http://www.w3.org/2001/XMLSchema-instance"><header><identifier>oai:oai.datacite.org:3659929</identifier><datestamp>2015-02-10T18:50:00Z</datestamp><setSpec>CDL</setSpec><setSpec>CDL.DRYAD</setSpec></header><metadata><oai_datacite xmlns="http://schema.datacite.org/oai/oai-1.0/" xsi:schemaLocation="http://schema.datacite.org/oai/oai-1.0/ http://schema.datacite.org/oai/oai-1.0/oai.xsd"><isReferenceQuality>false</isReferenceQuality><schemaVersion>2.2</schemaVersion><datacentreSymbol>CDL.DRYAD</datacentreSymbol><payload><resource xmlns="http://datacite.org/schema/kernel-2.2" xmlns:dryad="http://purl.org/dryad/terms/" xmlns:dim="http://www.dspace.org/xmlns/dspace/dim" xmlns:dspace="http://www.dspace.org/xmlns/dspace/dim" xmlns:mets="http://www.loc.gov/METS/" xmlns:xsi="http://www.w3.org/2001/XMLSchema-instance" metadataVersionNumber="1" lastMetadataUpdate="2006-05-04" xsi:schemaLocation="http://datacite.org/schema/kernel-2.2 http://schema.datacite.org/meta/kernel-2.2/metadata.xsd">
  <identifier identifierType="DOI">10.5061/DRYAD.81K4V/1</identifier>
  <creators>
      <creator>
         <creatorName>Yates, Matthew C.</creatorName>
      </creator>
      <creator>
         <creatorName>Fraser, Dylan J.</creatorName>
      </creator>
  </creators>
  <titles>
      <title>Source.Population.Size.Performance.In.Novel.Environments</title>
  </titles>
  <publisher>Dryad Digital Repository</publisher>
  <publicationYear>2014</publicationYear>
  <subjects>
      <subject>Population size</subject>
      <subject>Adaptation</subject>
      <subject>Reciprocal Transplant</subject>
      <subject>Conservation Biology</subject>
      <subject>Natural Selection and Contemporary Evolution</subject>
      <subject>Population Dynamics</subject>
      <subject>Translocation</subject>
      <subject>Meta-Analysis</subject>
      <subject>Contemporary Evolution</subject>
  </subjects>
  <dates>
      <date dateType="Accepted">2014-05-27</date>
  </dates>
  <resourceType resourceTypeGeneral="Dataset">DataFile</resourceType>
  <relatedIdentifiers>
      <relatedIdentifier relationType="IsPartOf" relatedIdentifierType="DOI">10.5061/DRYAD.81K4V</relatedIdentifier>
  </relatedIdentifiers>
  <sizes>
      <size>162038 bytes</size>
  </sizes>
  <rights>http://creativecommons.org/publicdomain/zero/1.0/</rights>
  <descriptions>
      <description descriptionType="Other">Meta-analysis data: Performance of natural populations when transplanted to novel natural environments, with associated source population size information.</description>
  </descriptions>
</resource></payload></oai_datacite></metadata></record>
