<record xmlns="http://www.openarchives.org/OAI/2.0/" xmlns:xsi="http://www.w3.org/2001/XMLSchema-instance"><header><identifier>oai:oai.datacite.org:3753283</identifier><datestamp>2014-12-10T04:18:10Z</datestamp><setSpec>CDL</setSpec><setSpec>CDL.DRYAD</setSpec></header><metadata><oai_datacite xmlns="http://schema.datacite.org/oai/oai-1.0/" xsi:schemaLocation="http://schema.datacite.org/oai/oai-1.0/ http://schema.datacite.org/oai/oai-1.0/oai.xsd"><isReferenceQuality>false</isReferenceQuality><schemaVersion>2.2</schemaVersion><datacentreSymbol>CDL.DRYAD</datacentreSymbol><payload><resource xmlns="http://datacite.org/schema/kernel-2.2" xmlns:dryad="http://purl.org/dryad/terms/" xmlns:dim="http://www.dspace.org/xmlns/dspace/dim" xmlns:dspace="http://www.dspace.org/xmlns/dspace/dim" xmlns:mets="http://www.loc.gov/METS/" xmlns:xsi="http://www.w3.org/2001/XMLSchema-instance" metadataVersionNumber="1" lastMetadataUpdate="2006-05-04" xsi:schemaLocation="http://datacite.org/schema/kernel-2.2 http://schema.datacite.org/meta/kernel-2.2/metadata.xsd">
  <identifier identifierType="DOI">10.5061/DRYAD.3QV3P/1</identifier>
  <creators>
      <creator>
         <creatorName>Maino, James L.</creatorName>
      </creator>
      <creator>
         <creatorName>Kearney, Michael Ray</creatorName>
      </creator>
  </creators>
  <titles>
      <title>Insect ontogenetic respiration</title>
  </titles>
  <publisher>Dryad Digital Repository</publisher>
  <publicationYear>2014</publicationYear>
  <subjects>
      <subject>Allometry</subject>
      <subject>Physiological Ecology</subject>
      <subject>Theoretical Ecology</subject>
      <subject>Energetics</subject>
      <subject>Individual Based Modeling</subject>
      <subject>Insect</subject>
      <subject>Respiration</subject>
      <subject>Oxygen Consumption</subject>
  </subjects>
  <dates>
      <date dateType="Accepted">2014-07-22</date>
  </dates>
  <resourceType resourceTypeGeneral="Dataset">DataFile</resourceType>
  <relatedIdentifiers>
      <relatedIdentifier relationType="IsPartOf" relatedIdentifierType="DOI">10.5061/DRYAD.3QV3P</relatedIdentifier>
  </relatedIdentifiers>
  <sizes>
      <size>93273 bytes</size>
  </sizes>
  <rights>http://creativecommons.org/publicdomain/zero/1.0/</rights>
  <descriptions>
      <description descriptionType="Other">This data set includes respiration measurements on 50 insects across various stages of ontogenetic development (embryonic, immature, and pupal respiration). The data were compiled from the literature with references and comments given in the  document.</description>
  </descriptions>
</resource></payload></oai_datacite></metadata></record>
