<record xmlns="http://www.openarchives.org/OAI/2.0/" xmlns:xsi="http://www.w3.org/2001/XMLSchema-instance"><header><identifier>oai:oai.datacite.org:3857643</identifier><datestamp>2014-10-27T20:19:09Z</datestamp><setSpec>CDL</setSpec><setSpec>CDL.DRYAD</setSpec></header><metadata><oai_datacite xmlns="http://schema.datacite.org/oai/oai-1.0/" xsi:schemaLocation="http://schema.datacite.org/oai/oai-1.0/ http://schema.datacite.org/oai/oai-1.0/oai.xsd"><isReferenceQuality>false</isReferenceQuality><schemaVersion>2.2</schemaVersion><datacentreSymbol>CDL.DRYAD</datacentreSymbol><payload><resource xmlns="http://datacite.org/schema/kernel-2.2" xmlns:dryad="http://purl.org/dryad/terms/" xmlns:dim="http://www.dspace.org/xmlns/dspace/dim" xmlns:dspace="http://www.dspace.org/xmlns/dspace/dim" xmlns:mets="http://www.loc.gov/METS/" xmlns:xsi="http://www.w3.org/2001/XMLSchema-instance" metadataVersionNumber="1" lastMetadataUpdate="2006-05-04" xsi:schemaLocation="http://datacite.org/schema/kernel-2.2 http://schema.datacite.org/meta/kernel-2.2/metadata.xsd">
  <identifier identifierType="DOI">10.5061/DRYAD.JK68B</identifier>
  <creators>
      <creator>
         <creatorName>Zhou, Fen</creatorName>
      </creator>
      <creator>
         <creatorName>Zhang, Yikui</creatorName>
      </creator>
      <creator>
         <creatorName>Chen, Ding</creatorName>
      </creator>
      <creator>
         <creatorName>Su, Zhitao</creatorName>
      </creator>
      <creator>
         <creatorName>Jin, Ling</creatorName>
      </creator>
      <creator>
         <creatorName>Wang, Lei</creatorName>
      </creator>
      <creator>
         <creatorName>Hu, Zhixiang</creatorName>
      </creator>
      <creator>
         <creatorName>Ke, Zhisheng</creatorName>
      </creator>
      <creator>
         <creatorName>Song, Zongming</creatorName>
      </creator>
  </creators>
  <titles>
      <title>Data from: Potential role of Cyr61 induced degeneration of human M&#252;ller cells in diabetic retinopathy</title>
  </titles>
  <publisher>Dryad Digital Repository</publisher>
  <publicationYear>2014</publicationYear>
  <subjects>
      <subject>High glucose</subject>
      <subject>diabetic retinopathy</subject>
      <subject>Cyr61</subject>
      <subject>degeneration</subject>
      <subject>retinal M&#252;ller cells</subject>
  </subjects>
  <resourceType resourceTypeGeneral="Dataset">DataPackage</resourceType>
  <alternateIdentifiers>
      <alternateIdentifier alternateIdentifierType="citation">Zhou F, Zhang Y, Chen D, Su Z, Jin L, Wang L, Hu Z, Ke Z, Song Z (2014) Potential role of Cyr61 induced degeneration of human M&#252;ller cells in diabetic retinopathy. PLoS ONE 9(10): e109418.</alternateIdentifier>
  </alternateIdentifiers>
  <relatedIdentifiers>
      <relatedIdentifier relationType="HasPart" relatedIdentifierType="DOI">10.5061/DRYAD.JK68B/1</relatedIdentifier>
      <relatedIdentifier relationType="IsReferencedBy" relatedIdentifierType="DOI">10.1371/JOURNAL.PONE.0109418</relatedIdentifier>
  </relatedIdentifiers>
  <rights>http://creativecommons.org/publicdomain/zero/1.0/</rights>
</resource></payload></oai_datacite></metadata></record>
