<record xmlns="http://www.openarchives.org/OAI/2.0/" xmlns:xsi="http://www.w3.org/2001/XMLSchema-instance"><header><identifier>oai:oai.datacite.org:6287487</identifier><datestamp>2015-07-20T18:48:22Z</datestamp><setSpec>CDL</setSpec><setSpec>CDL.DRYAD</setSpec></header><metadata><oai_datacite xmlns="http://schema.datacite.org/oai/oai-1.0/" xsi:schemaLocation="http://schema.datacite.org/oai/oai-1.0/ http://schema.datacite.org/oai/oai-1.0/oai.xsd"><isReferenceQuality>false</isReferenceQuality><schemaVersion>2.2</schemaVersion><datacentreSymbol>CDL.DRYAD</datacentreSymbol><payload><resource xmlns="http://datacite.org/schema/kernel-2.2" xmlns:dryad="http://purl.org/dryad/terms/" xmlns:dim="http://www.dspace.org/xmlns/dspace/dim" xmlns:dspace="http://www.dspace.org/xmlns/dspace/dim" xmlns:mets="http://www.loc.gov/METS/" xmlns:xsi="http://www.w3.org/2001/XMLSchema-instance" metadataVersionNumber="1" lastMetadataUpdate="2006-05-04" xsi:schemaLocation="http://datacite.org/schema/kernel-2.2 http://schema.datacite.org/meta/kernel-2.2/metadata.xsd">
  <identifier identifierType="DOI">10.5061/DRYAD.8BS2B/3</identifier>
  <creators>
      <creator>
         <creatorName>Giles, Sam</creatorName>
      </creator>
      <creator>
         <creatorName>Coates, Michael I.</creatorName>
      </creator>
      <creator>
         <creatorName>Garwood, Russell J.</creatorName>
      </creator>
      <creator>
         <creatorName>Brazeau, Martin D.</creatorName>
      </creator>
      <creator>
         <creatorName>Atwood, Robert</creatorName>
      </creator>
      <creator>
         <creatorName>Johanson, Zerina</creatorName>
      </creator>
      <creator>
         <creatorName>Friedman, Matt</creatorName>
      </creator>
  </creators>
  <titles>
      <title>Cheirolepis hyomandibula</title>
  </titles>
  <publisher>Dryad Digital Repository</publisher>
  <publicationYear>2015</publicationYear>
  <subjects>
      <subject>computed tomography</subject>
      <subject>Devonian</subject>
      <subject>neurocranium</subject>
      <subject>palaeontology</subject>
      <subject>Devonian</subject>
      <subject>Cheirolepis</subject>
  </subjects>
  <dates>
      <date dateType="Accepted">2015-07-20</date>
  </dates>
  <resourceType resourceTypeGeneral="Dataset">DataFile</resourceType>
  <relatedIdentifiers>
      <relatedIdentifier relationType="IsPartOf" relatedIdentifierType="DOI">10.5061/DRYAD.8BS2B</relatedIdentifier>
  </relatedIdentifiers>
  <sizes>
      <size>3523685 bytes</size>
  </sizes>
  <rights>http://creativecommons.org/publicdomain/zero/1.0/</rights>
  <descriptions>
      <description descriptionType="Other">PLY file of the hyomandibula of Cheirolepis.</description>
  </descriptions>
</resource></payload></oai_datacite></metadata></record>
