<record xmlns="http://www.openarchives.org/OAI/2.0/" xmlns:xsi="http://www.w3.org/2001/XMLSchema-instance"><header><identifier>oai:oai.datacite.org:6345601</identifier><datestamp>2015-06-29T19:35:12Z</datestamp><setSpec>CDL</setSpec><setSpec>CDL.DRYAD</setSpec></header><metadata><oai_datacite xmlns="http://schema.datacite.org/oai/oai-1.0/" xsi:schemaLocation="http://schema.datacite.org/oai/oai-1.0/ http://schema.datacite.org/oai/oai-1.0/oai.xsd"><isReferenceQuality>false</isReferenceQuality><schemaVersion>2.2</schemaVersion><datacentreSymbol>CDL.DRYAD</datacentreSymbol><payload><resource xmlns="http://datacite.org/schema/kernel-2.2" xmlns:dryad="http://purl.org/dryad/terms/" xmlns:dim="http://www.dspace.org/xmlns/dspace/dim" xmlns:dspace="http://www.dspace.org/xmlns/dspace/dim" xmlns:mets="http://www.loc.gov/METS/" xmlns:xsi="http://www.w3.org/2001/XMLSchema-instance" metadataVersionNumber="1" lastMetadataUpdate="2006-05-04" xsi:schemaLocation="http://datacite.org/schema/kernel-2.2 http://schema.datacite.org/meta/kernel-2.2/metadata.xsd">
  <identifier identifierType="DOI">10.5061/DRYAD.11385/1</identifier>
  <creators>
      <creator>
         <creatorName>Font&#250;rbel, Francisco E.</creatorName>
      </creator>
      <creator>
         <creatorName>Jordano, Pedro</creatorName>
      </creator>
      <creator>
         <creatorName>Medel, Rodrigo</creatorName>
      </creator>
  </creators>
  <titles>
      <title>Pollination and seed dispersal data</title>
  </titles>
  <publisher>Dryad Digital Repository</publisher>
  <publicationYear>2015</publicationYear>
  <subjects>
      <subject>Moran&#8217;s eigenvector maps</subject>
      <subject>Plant population and community dynamics</subject>
      <subject>SADIE</subject>
      <subject>Southern Chile</subject>
      <subject>Dromiciops gliroides</subject>
      <subject>Sephanoides sephaniodes</subject>
      <subject>Tristerix corymbosus</subject>
  </subjects>
  <dates>
      <date dateType="Accepted">2015-06-29</date>
  </dates>
  <resourceType resourceTypeGeneral="Dataset">DataFile</resourceType>
  <relatedIdentifiers>
      <relatedIdentifier relationType="IsPartOf" relatedIdentifierType="DOI">10.5061/DRYAD.11385</relatedIdentifier>
  </relatedIdentifiers>
  <sizes>
      <size>8362 bytes</size>
      <size>1763 bytes</size>
  </sizes>
  <rights>http://creativecommons.org/publicdomain/zero/1.0/</rights>
  <descriptions>
      <description descriptionType="Other">This CSV file contains all the original field data collected. Please refer to the ReadMe file for an explanation of the column headers.</description>
  </descriptions>
</resource></payload></oai_datacite></metadata></record>
