<record xmlns="http://www.openarchives.org/OAI/2.0/" xmlns:xsi="http://www.w3.org/2001/XMLSchema-instance"><header><identifier>oai:oai.datacite.org:79773</identifier><datestamp>2014-05-29T19:39:38Z</datestamp><setSpec>CDL</setSpec><setSpec>CDL.DRYAD</setSpec></header><metadata><oai_datacite xmlns="http://schema.datacite.org/oai/oai-1.0/" xsi:schemaLocation="http://schema.datacite.org/oai/oai-1.0/ http://schema.datacite.org/oai/oai-1.0/oai.xsd"><isReferenceQuality>false</isReferenceQuality><schemaVersion>2.2</schemaVersion><datacentreSymbol>CDL.DRYAD</datacentreSymbol><payload><resource xmlns="http://datacite.org/schema/kernel-2.2" xmlns:dryad="http://purl.org/dryad/terms/" xmlns:dim="http://www.dspace.org/xmlns/dspace/dim" xmlns:dspace="http://www.dspace.org/xmlns/dspace/dim" xmlns:mets="http://www.loc.gov/METS/" xmlns:xsi="http://www.w3.org/2001/XMLSchema-instance" metadataVersionNumber="1" lastMetadataUpdate="2006-05-04" xsi:schemaLocation="http://datacite.org/schema/kernel-2.2 http://schema.datacite.org/meta/kernel-2.2/metadata.xsd">
  <identifier identifierType="DOI">10.5061/DRYAD.3MV8V434</identifier>
  <creators>
      <creator>
         <creatorName>Bienert, Friederike</creatorName>
      </creator>
      <creator>
         <creatorName>De Danieli, S&#233;bastien</creatorName>
      </creator>
      <creator>
         <creatorName>Miquel, Christian</creatorName>
      </creator>
      <creator>
         <creatorName>Coissac, Eric</creatorName>
      </creator>
      <creator>
         <creatorName>Poillot, Carole</creatorName>
      </creator>
      <creator>
         <creatorName>Brun, Jean-Jacques</creatorName>
      </creator>
      <creator>
         <creatorName>Taberlet, Pierre</creatorName>
      </creator>
  </creators>
  <titles>
      <title>Data from: Tracking earthworm communities from soil DNA</title>
  </titles>
  <publisher>Dryad Digital Repository</publisher>
  <publicationYear>2011</publicationYear>
  <subjects>
      <subject>Community Ecology</subject>
      <subject>DNA Barcoding</subject>
      <subject>Invertebrates</subject>
      <subject>Population Ecology</subject>
      <subject>DNA metabarcoding</subject>
      <subject>France</subject>
      <subject>Grenoble</subject>
      <subject>Chartreuse</subject>
      <subject>Aporrectodea icterica</subject>
      <subject>Aporrectodea longa</subject>
      <subject>Aporrectodea cupulifera</subject>
      <subject>Octolasion cyaneum</subject>
      <subject>Lumbricus terrestris</subject>
      <subject>Octolasion tyrtaeum</subject>
      <subject>Aporrectodea nocturna</subject>
      <subject>Lumbricus castaneus</subject>
      <subject>Allobophora chlorotica</subject>
      <subject>Aporrectodea rosea</subject>
  </subjects>
  <resourceType resourceTypeGeneral="Dataset">DataPackage</resourceType>
  <alternateIdentifiers>
      <alternateIdentifier alternateIdentifierType="citation">Bienert F, De Danieli S, Miquel C, Coissac E, Poillot C, Brun J, Taberlet P (2011) Tracking earthworm communities from soil DNA. Molecular Ecology 21(8): 2017-2030.</alternateIdentifier>
  </alternateIdentifiers>
  <relatedIdentifiers>
      <relatedIdentifier relationType="HasPart" relatedIdentifierType="DOI">10.5061/DRYAD.3MV8V434/1</relatedIdentifier>
      <relatedIdentifier relationType="HasPart" relatedIdentifierType="DOI">10.5061/DRYAD.3MV8V434/2</relatedIdentifier>
      <relatedIdentifier relationType="HasPart" relatedIdentifierType="DOI">10.5061/DRYAD.3MV8V434/3</relatedIdentifier>
      <relatedIdentifier relationType="HasPart" relatedIdentifierType="DOI">10.5061/DRYAD.3MV8V434/4</relatedIdentifier>
      <relatedIdentifier relationType="IsReferencedBy" relatedIdentifierType="DOI">10.1111/J.1365-294X.2011.05407.X</relatedIdentifier>
      <relatedIdentifier relationType="IsReferencedBy" relatedIdentifierType="DOI"/>
  </relatedIdentifiers>
  <rights>http://creativecommons.org/publicdomain/zero/1.0/</rights>
</resource></payload></oai_datacite></metadata></record>
